test_pypi_hfudev/__init__.py
test_pypi_hfudev/test_pypi_hfudev.py
test_pypi_hfudev-1.0.0rc0.dist-info/LICENSE
test_pypi_hfudev-1.0.0rc0.dist-info/METADATA
test_pypi_hfudev-1.0.0rc0.dist-info/WHEEL
test_pypi_hfudev-1.0.0rc0.dist-info/RECORD
